gai/_utils/_docker_utils.py
gai/_utils/_scripts_utils.py
gai/_utils/devtools.py
gai/lib/api.py
gai/lib/color.py
gai/lib/constants.py
gai/lib/diagnostics.py
gai/lib/errors.py
gai/lib/http_utils.py
gai/lib/image_utils.py
gai/lib/logging.py
gai/lib/prompts.py
gai/lib/strings.py
gai/lib/tests.py
gai/lib/utils.py
gai/lib/config/__init__.py
gai/lib/config/config_base.py
gai/lib/config/config_helper.py
gai/lib/config/download_config.py
gai/lib/config/gai_client_config.py
gai/lib/config/gai_config.py
gai/lib/config/gai_generator_config.py
gai/lib/config/gai_tool_config.py
gai_lib-0.181.11.dist-info/METADATA
gai_lib-0.181.11.dist-info/WHEEL
gai_lib-0.181.11.dist-info/licenses/LICENSE
gai_lib-0.181.11.dist-info/RECORD
