Metadata-Version: 2.4
Name: gai-lib
Version: 0.181.11
Summary: Refer to https://gai-labs.github.io/gai for more information
Project-URL: documentation, https://gai-labs.github.io/gai/docs
Author-email: kakkoii1337 <kakkoii1337@gmail.com>
License: MIT License
License-File: LICENSE
Classifier: Development Status :: 3 - Alpha
Classifier: Intended Audience :: Developers
Classifier: Intended Audience :: Science/Research
Classifier: License :: OSI Approved :: MIT License
Classifier: Operating System :: OS Independent
Classifier: Programming Language :: Python :: 3.10
Classifier: Topic :: Scientific/Engineering :: Artificial Intelligence
Classifier: Topic :: Software Development
Classifier: Topic :: Software Development :: Libraries :: Python Modules
Requires-Python: >=3.10
Requires-Dist: fastapi>=0.115.12
Requires-Dist: huggingface-hub<0.25,>=0.24.5
Requires-Dist: nest-asyncio>=1.6.0
Requires-Dist: openai<2.0.0,>=1.43.0
Requires-Dist: pydantic>=1.0
Requires-Dist: python-dotenv<2.0,>=1.0.1
Requires-Dist: pyyaml>=6.0.2
Requires-Dist: rich<14.0,>=13.7.1
Requires-Dist: toml<0.11,>=0.10.2
Provides-Extra: dev
Requires-Dist: build>=1.2.2.post1; extra == 'dev'
Requires-Dist: flake8<8.0,>=7.1.1; extra == 'dev'
Requires-Dist: ipykernel<7.0,>=6.29.5; extra == 'dev'
Requires-Dist: jupyterlab>=4.4.2; extra == 'dev'
Requires-Dist: keyrings-alt<6.0,>=5.0.1; extra == 'dev'
Requires-Dist: notebook>=7.4.2; extra == 'dev'
Requires-Dist: nox<2025.0,>=2024.4.15; extra == 'dev'
Requires-Dist: pytest-asyncio==0.25.2; extra == 'dev'
Requires-Dist: pytest-ordering<1.0,>=0.6; extra == 'dev'
Requires-Dist: pytest>=8.3.5; extra == 'dev'
Requires-Dist: twine>=6.1.0; extra == 'dev'
Requires-Dist: wheel>=0.45.1; extra == 'dev'
